ConversationInferenceTree/__init__.py
ConversationInferenceTree/agent.py
ConversationInferenceTree/inference_tree.py
ConversationInferenceTree/logger.py
ConversationInferenceTree/model_wrapper.py
ConversationInferenceTree/reddit_wrapper.py
ConversationInferenceTree/tree.py
conversationinferencetree-0.1.2.dist-info/licenses/LICENSE
conversationinferencetree-0.1.2.dist-info/METADATA
conversationinferencetree-0.1.2.dist-info/WHEEL
conversationinferencetree-0.1.2.dist-info/top_level.txt
conversationinferencetree-0.1.2.dist-info/RECORD
