Metadata-Version: 2.4
Name: ConversationInferenceTree
Version: 0.1.2
Summary: This package was made to allow a user to generate a summarized explanation of any provided reddit thread, by applying a series of user-created questions in a predetermined logical sequence.  The intended use case is to allow the user to extract the underlying reasoning of conversations about a given subject at a massive scale, then save those inferences to create a dataset or report.
Author: Brayden Cloutier
License:                                  Apache License
Requires-Python: >=3.8
License-File: LICENSE
Requires-Dist: cligraph==0.1.4
Requires-Dist: huggingface_hub==0.32.4
Requires-Dist: nvidia_ml_py==12.575.51
Requires-Dist: openai==1.97.0
Requires-Dist: praw==7.8.1
Requires-Dist: pynvml==12.0.0
Requires-Dist: python-dotenv==1.1.1
Requires-Dist: transformers==4.52.4
Requires-Dist: treelib==1.7.1
Requires-Dist: torch==2.7.1
Dynamic: license-file
